fragua_sets/__init__.py
fragua_sets/functions/__init__.py
fragua_sets/functions/extraction.py
fragua_sets/functions/loading.py
fragua_sets/functions/transformation.py
fragua_sets/functions/utility.py
fragua_sets/sets/__init__.py
fragua_sets/sets/sets_config.py
fragua_sets/utils/__init__.py
fragua_sets/utils/enums/__init__.py
fragua_sets/utils/enums/functions.py
fragua_sets/utils/enums/sets.py
fragua_sets-1.5.dist-info/licenses/LICENSE
fragua_sets-1.5.dist-info/METADATA
fragua_sets-1.5.dist-info/WHEEL
fragua_sets-1.5.dist-info/top_level.txt
fragua_sets-1.5.dist-info/RECORD
