Metadata-Version: 2.4
Name: fragua-sets
Version: 1.5
Summary: Package with fragua sets with reutilizable functions for ETL process.
Home-page: https://github.com/SagoDev/fragua-sets
Author: SagoDev
Requires-Python: >=3.10
License-File: LICENSE
Requires-Dist: fragua
Requires-Dist: requests
Requires-Dist: pandas
Requires-Dist: numpy
Requires-Dist: sqlalchemy
Dynamic: author
Dynamic: description
Dynamic: description-content-type
Dynamic: home-page
Dynamic: license-file
Dynamic: requires-dist
Dynamic: requires-python
Dynamic: summary
